{"docSchemaVersion":1.0,"id":"66f54482a6b1e9f3a9186879","meta":{"actionsByState":{"active":0.0,"fail":0.0,"queued":0.0,"success":0.0},"assets":[],"audit":{"created":{"authProvider":{"id":"","title":"Swimlane"},"date":"2024-09-26T11:24:50.172+00:00","user":{"id":"7c0f03b8-4ea6-4567-a9b2-1be568e5e475","username":"koushik.kumar+git-test@swimlane.com"}},"modified":{"authProvider":{"id":"","title":"Swimlane"},"date":"2024-09-26T11:24:50.172+00:00","user":{"id":"7c0f03b8-4ea6-4567-a9b2-1be568e5e475","username":"koushik.kumar+git-test@swimlane.com"}},"version":1.0},"componentId":"aS9A5tmGDMK9dzNgm","connectors":[],"enabled":true,"playbooks":[],"pools":[],"sharingUid":"53377a54-4bc6-4298-8f5f-6977eb7d4c54","src":"schema: playbook/2\nname: component_aS9A5tmGDMK9dzNgm_playbook\nactions:\n  NOOP:\n    meta: {}\n    title: NOOP\n    type: transformation\n    delay: 0\n    pool: \"\"\n    on-success: []\n    on-failure: []\n    on-complete: []\n    publish: {}\n    post: {}\n    timeout: 0\n    description: This action does nothing.  Action is required to enable interface.\n    transformations: {}\n    entrypoint: \"\"\nmeta: {}\ntitle: component_aS9A5tmGDMK9dzNgm_playbook\ndescription: \"\"\nnamespace: $default\nentrypoints:\n- NOOP\npool: \"\"\ntimeout: 0\npublish:\n  alert:\n    $:ref: $inputs.alert\nenvironment: {}\ninputs:\n  type: object\n  properties:\n    alert:\n      type: object\n      properties:\n        alert_categories:\n          title: alert_category\n          description: alert_category\n          type: array\n          items:\n            type: string\n        alert_created_timestamp:\n          title: alert_created_timestamp\n          description: alert_created_timestamp\n          type: string\n        alert_description:\n          title: Description\n          description: alert_description\n          type: string\n        alert_end_timestamp:\n          title: alert_end_timestamp\n          description: alert_end_timestamp\n          type: string\n        alert_impacted_hostnames:\n          title: alert_impacted_hostnames\n          description: alert_impacted_hostnames\n          type: array\n          items:\n            type: string\n        alert_impacted_ip_addresses:\n          title: alert_impacted_ip_addresses\n          description: alert_impacted_ip_addresses\n          type: array\n          items:\n            type: string\n        alert_impacted_usernames:\n          title: alert_impacted_usernames\n          description: alert_impacted_usernames\n          type: array\n          items:\n            type: string\n        alert_ingested_timestamp:\n          title: alert_ingested_timestamp\n          description: alert_ingested_timestamp\n          type: string\n        alert_mitre_attack_tactic_technique:\n          title: MITRE Attack Tactic/Technique\n          description: alert_mitre_attack_phases\n          type: array\n          items:\n            type: object\n            properties:\n              tactics:\n                title: Tactics\n                description: The a list of tactic ID's/names that are associated with the attack technique, as defined by <a target='_blank' href='https://attack.mitre.org/wiki/ATT&CK_Matrix'>ATT&CK Matrix<sup>TM</sup></a>.\n                type: array\n                items:\n                  type: object\n                  properties:\n                    name:\n                      title: Name\n                      description: The tactic name that is associated with the attack technique, as defined by <a target='_blank' href='https://attack.mitre.org/wiki/ATT&CK_Matrix'>ATT&CK Matrix<sup>TM</sup></a>.\n                      type: string\n                    uid:\n                      title: Unique ID\n                      description: The tactic ID that is associated with the attack technique, as defined by <a target='_blank' href='https://attack.mitre.org/wiki/ATT&CK_Matrix'>ATT&CK Matrix<sup>TM</sup></a>.\n                      type: string\n                  required:\n                  - uid\n              technique:\n                title: Technique\n                description: The attack technique.\n                type: object\n                properties:\n                  name:\n                    title: Name\n                    description: \"The name of the attack technique, as defined by <a target='_blank' href='https://attack.mitre.org/wiki/ATT&CK_Matrix'>ATT&CK Matrix<sup>TM</sup></a>. For example: <code>Drive-by Compromise</code>.\"\n                    type: string\n                  uid:\n                    title: Unique ID\n                    description: \"The unique identifier of the attack technique, as defined by <a target='_blank' href='https://attack.mitre.org/wiki/ATT&CK_Matrix'>ATT&CK Matrix<sup>TM</sup></a>. For example: <code>T1189</code>.\"\n                    type: string\n                required:\n                - uid\n              version:\n                title: Version\n                description: The ATT&CK Matrix version.\n                type: string\n        alert_organization:\n          title: alert_organization\n          description: alert_organization\n          type: string\n        alert_originating_files:\n          title: alert_originating_files\n          description: alert_originating_files\n          type: array\n          items:\n            type: object\n            properties:\n              content:\n                title: content\n                description: content\n                type: object\n                properties:\n                  base64:\n                    title: base64\n                    description: base64\n                    type: string\n                  turbine_attachment:\n                    title: turbine_attachment\n                    description: turbine_attachment\n                    type: object\n              file_accessed:\n                title: file_accessed\n                description: file_accessed\n                type: string\n              file_created:\n                title: file_created\n                description: file_created\n                type: string\n              file_hashes:\n                title: file_hashes\n                description: file_hashes\n                type: array\n                items:\n                  type: object\n                  properties:\n                    hash_algorithm:\n                      title: Algorithm Name\n                      description: Algorithm Name\n                      type: string\n                    hash_value:\n                      title: Hash Value\n                      description: Hash Value\n                      type: string\n                  required:\n                  - hash_algorithm\n                  - hash_value\n              file_modified:\n                title: file_modified\n                description: file_modified\n                type: string\n              file_name:\n                title: file_name\n                description: file_name\n                type: string\n              file_name_enc:\n                title: file_name_enc\n                description: file_name_enc\n                type: string\n              file_size:\n                title: file_size\n                description: file_size\n                type: integer\n              mime_type:\n                title: mime_type\n                description: mime_type\n                type: string\n              observables:\n                title: observables\n                description: observables\n                type: array\n                items:\n                  type: object\n                  properties:\n                    observable_enrichments:\n                      title: observable_enrichments\n                      description: observable_enrichments\n                      type: array\n                      items:\n                        type: object\n                        properties:\n                          enrichment_context:\n                            title: enrichment_context\n                            description: enrichment_context\n                            type: string\n                          enrichment_permalink:\n                            title: enrichment_permalink\n                            description: enrichment_permalink\n                            type: string\n                          enrichment_provider:\n                            title: enrichment_provider\n                            description: The enrichment data provider name.\n                            type: string\n                          enrichment_raw_data:\n                            title: enrichment_raw-data\n                            description: enrichment_raw-data\n                            type: string\n                          enrichment_timestamp:\n                            title: enrichment_timestamp\n                            description: Datetime the enrichment was retrieved\n                            type: string\n                          enrichment_type:\n                            title: enrichment_type\n                            description: 'The enrichment type. For example: location'\n                            type: string\n                          enrichment_verdict:\n                            title: enrichment_verdict\n                            description: The reputation verdict\n                            type: string\n                        required:\n                        - enrichment_type\n                    observable_metadata:\n                      title: observable_metadata\n                      description: Observable Metadata\n                      type: object\n                    observable_primary_context:\n                      title: observable_primary_context\n                      description: observable_primary_context\n                      type: string\n                    observable_primary_permalink:\n                      title: observable_primary_permalink\n                      description: observable_primary_permalink\n                      type: string\n                    observable_primary_provider:\n                      title: observable_primary_provider\n                      description: observable_primary_provider\n                      type: string\n                    observable_primary_timestamp:\n                      title: observable_primary_timestamp\n                      description: observable_primary_timestamp\n                      type: string\n                    observable_primary_verdict:\n                      title: observable_primary_verdict\n                      description: observable_primary_verdict\n                      type: string\n                    observable_type:\n                      title: observable_type\n                      description: observable_type\n                      type: string\n                    observable_value:\n                      title: observable_value\n                      description: observable_value\n                      type: string\n                  required:\n                  - observable_type\n                  - observable_value\n        alert_permalink:\n          title: alert_permalink\n          description: alert_permalink\n          type: string\n        alert_provider:\n          title: alert_provider\n          description: alert_provider\n          type: string\n        alert_risk_score:\n          title: alert_risk_score\n          description: alert_risk_score\n          type: integer\n        alert_rules:\n          title: alert_rules\n          description: alert_rules\n          type: array\n          items:\n            type: object\n            properties:\n              rule_description:\n                title: rule_description\n                description: rule_description\n                type: string\n              rule_id:\n                title: rule_id\n                description: rule_id\n                type: string\n              rule_name:\n                title: rule_name\n                description: rule_name\n                type: string\n              rule_type:\n                title: rule_type\n                description: rule_type\n                type: string\n        alert_severity:\n          title: alert_severity\n          description: alert_severity\n          type: string\n        alert_start_timestamp:\n          title: alert_start_timestamp\n          description: alert_start_timestamp\n          type: string\n        alert_title:\n          title: Title\n          description: alert_title\n          type: string\n        alert_uid:\n          title: alert_uid\n          description: alert_uid\n          type: string\n        observables:\n          title: observables\n          description: observables\n          type: array\n          items:\n            type: object\n            properties:\n              observable_enrichments:\n                title: observable_enrichments\n                description: observable_enrichments\n                type: array\n                items:\n                  type: object\n                  properties:\n                    enrichment_context:\n                      title: enrichment_context\n                      description: enrichment_context\n                      type: string\n                    enrichment_permalink:\n                      title: enrichment_permalink\n                      description: enrichment_permalink\n                      type: string\n                    enrichment_provider:\n                      title: enrichment_provider\n                      description: The enrichment data provider name.\n                      type: string\n                    enrichment_raw_data:\n                      title: enrichment_raw-data\n                      description: enrichment_raw-data\n                      type: string\n                    enrichment_timestamp:\n                      title: enrichment_timestamp\n                      description: Datetime the enrichment was retrieved\n                      type: string\n                    enrichment_type:\n                      title: enrichment_type\n                      description: 'The enrichment type. For example: location'\n                      type: string\n                    enrichment_verdict:\n                      title: enrichment_verdict\n                      description: The reputation verdict\n                      type: string\n                  required:\n                  - enrichment_type\n              observable_metadata:\n                title: observable_metadata\n                description: Observable Metadata\n                type: object\n              observable_primary_context:\n                title: observable_primary_context\n                description: observable_primary_context\n                type: string\n              observable_primary_permalink:\n                title: observable_primary_permalink\n                description: observable_primary_permalink\n                type: string\n              observable_primary_provider:\n                title: observable_primary_provider\n                description: observable_primary_provider\n                type: string\n              observable_primary_timestamp:\n                title: observable_primary_timestamp\n                description: observable_primary_timestamp\n                type: string\n              observable_primary_verdict:\n                title: observable_primary_verdict\n                description: observable_primary_verdict\n                type: string\n              observable_type:\n                title: observable_type\n                description: observable_type\n                type: string\n              observable_value:\n                title: observable_value\n                description: observable_value\n                type: string\n            required:\n            - observable_type\n            - observable_value\n        raw_alert:\n          title: raw_alert\n          description: raw_alert\n          type: object\ntriggers: {}\n","store":{},"validation":{"valid":true}},"playbook":{"actions":{"NOOP":{"meta":{},"title":"NOOP","type":"transformation","delay":0,"pool":"","on-success":[],"on-failure":[],"on-complete":[],"publish":{},"post":{},"timeout":0,"description":"This action does nothing.  Action is required to enable interface.","transformations":{},"entrypoint":""}},"description":"","entrypoints":["NOOP"],"environment":{},"inputs":{"type":"object","properties":{"alert":{"type":"object","properties":{"alert_categories":{"title":"alert_category","description":"alert_category","type":"array","items":{"type":"string"}},"alert_created_timestamp":{"title":"alert_created_timestamp","description":"alert_created_timestamp","type":"string"},"alert_description":{"title":"Description","description":"alert_description","type":"string"},"alert_end_timestamp":{"title":"alert_end_timestamp","description":"alert_end_timestamp","type":"string"},"alert_impacted_hostnames":{"title":"alert_impacted_hostnames","description":"alert_impacted_hostnames","type":"array","items":{"type":"string"}},"alert_impacted_ip_addresses":{"title":"alert_impacted_ip_addresses","description":"alert_impacted_ip_addresses","type":"array","items":{"type":"string"}},"alert_impacted_usernames":{"title":"alert_impacted_usernames","description":"alert_impacted_usernames","type":"array","items":{"type":"string"}},"alert_ingested_timestamp":{"title":"alert_ingested_timestamp","description":"alert_ingested_timestamp","type":"string"},"alert_mitre_attack_tactic_technique":{"title":"MITRE Attack Tactic/Technique","description":"alert_mitre_attack_phases","type":"array","items":{"type":"object","properties":{"tactics":{"title":"Tactics","description":"The a list of tactic ID's/names that are associated with the attack technique, as defined by <a target='_blank' href='https://attack.mitre.org/wiki/ATT&CK_Matrix'>ATT&CK Matrix<sup>TM</sup></a>.","type":"array","items":{"type":"object","properties":{"name":{"title":"Name","description":"The tactic name that is associated with the attack technique, as defined by <a target='_blank' href='https://attack.mitre.org/wiki/ATT&CK_Matrix'>ATT&CK Matrix<sup>TM</sup></a>.","type":"string"},"uid":{"title":"Unique ID","description":"The tactic ID that is associated with the attack technique, as defined by <a target='_blank' href='https://attack.mitre.org/wiki/ATT&CK_Matrix'>ATT&CK Matrix<sup>TM</sup></a>.","type":"string"}},"required":["uid"]}},"technique":{"title":"Technique","description":"The attack technique.","type":"object","properties":{"name":{"title":"Name","description":"The name of the attack technique, as defined by <a target='_blank' href='https://attack.mitre.org/wiki/ATT&CK_Matrix'>ATT&CK Matrix<sup>TM</sup></a>. For example: <code>Drive-by Compromise</code>.","type":"string"},"uid":{"title":"Unique ID","description":"The unique identifier of the attack technique, as defined by <a target='_blank' href='https://attack.mitre.org/wiki/ATT&CK_Matrix'>ATT&CK Matrix<sup>TM</sup></a>. For example: <code>T1189</code>.","type":"string"}},"required":["uid"]},"version":{"title":"Version","description":"The ATT&CK Matrix version.","type":"string"}}}},"alert_organization":{"title":"alert_organization","description":"alert_organization","type":"string"},"alert_originating_files":{"title":"alert_originating_files","description":"alert_originating_files","type":"array","items":{"type":"object","properties":{"content":{"title":"content","description":"content","type":"object","properties":{"base64":{"title":"base64","description":"base64","type":"string"},"turbine_attachment":{"title":"turbine_attachment","description":"turbine_attachment","type":"object"}}},"file_accessed":{"title":"file_accessed","description":"file_accessed","type":"string"},"file_created":{"title":"file_created","description":"file_created","type":"string"},"file_hashes":{"title":"file_hashes","description":"file_hashes","type":"array","items":{"type":"object","properties":{"hash_algorithm":{"title":"Algorithm Name","description":"Algorithm Name","type":"string"},"hash_value":{"title":"Hash Value","description":"Hash Value","type":"string"}},"required":["hash_algorithm","hash_value"]}},"file_modified":{"title":"file_modified","description":"file_modified","type":"string"},"file_name":{"title":"file_name","description":"file_name","type":"string"},"file_name_enc":{"title":"file_name_enc","description":"file_name_enc","type":"string"},"file_size":{"title":"file_size","description":"file_size","type":"integer"},"mime_type":{"title":"mime_type","description":"mime_type","type":"string"},"observables":{"title":"observables","description":"observables","type":"array","items":{"type":"object","properties":{"observable_enrichments":{"title":"observable_enrichments","description":"observable_enrichments","type":"array","items":{"type":"object","properties":{"enrichment_context":{"title":"enrichment_context","description":"enrichment_context","type":"string"},"enrichment_permalink":{"title":"enrichment_permalink","description":"enrichment_permalink","type":"string"},"enrichment_provider":{"title":"enrichment_provider","description":"The enrichment data provider name.","type":"string"},"enrichment_raw_data":{"title":"enrichment_raw-data","description":"enrichment_raw-data","type":"string"},"enrichment_timestamp":{"title":"enrichment_timestamp","description":"Datetime the enrichment was retrieved","type":"string"},"enrichment_type":{"title":"enrichment_type","description":"The enrichment type. For example: location","type":"string"},"enrichment_verdict":{"title":"enrichment_verdict","description":"The reputation verdict","type":"string"}},"required":["enrichment_type"]}},"observable_metadata":{"title":"observable_metadata","description":"Observable Metadata","type":"object"},"observable_primary_context":{"title":"observable_primary_context","description":"observable_primary_context","type":"string"},"observable_primary_permalink":{"title":"observable_primary_permalink","description":"observable_primary_permalink","type":"string"},"observable_primary_provider":{"title":"observable_primary_provider","description":"observable_primary_provider","type":"string"},"observable_primary_timestamp":{"title":"observable_primary_timestamp","description":"observable_primary_timestamp","type":"string"},"observable_primary_verdict":{"title":"observable_primary_verdict","description":"observable_primary_verdict","type":"string"},"observable_type":{"title":"observable_type","description":"observable_type","type":"string"},"observable_value":{"title":"observable_value","description":"observable_value","type":"string"}},"required":["observable_type","observable_value"]}}}}},"alert_permalink":{"title":"alert_permalink","description":"alert_permalink","type":"string"},"alert_provider":{"title":"alert_provider","description":"alert_provider","type":"string"},"alert_risk_score":{"title":"alert_risk_score","description":"alert_risk_score","type":"integer"},"alert_rules":{"title":"alert_rules","description":"alert_rules","type":"array","items":{"type":"object","properties":{"rule_description":{"title":"rule_description","description":"rule_description","type":"string"},"rule_id":{"title":"rule_id","description":"rule_id","type":"string"},"rule_name":{"title":"rule_name","description":"rule_name","type":"string"},"rule_type":{"title":"rule_type","description":"rule_type","type":"string"}}}},"alert_severity":{"title":"alert_severity","description":"alert_severity","type":"string"},"alert_start_timestamp":{"title":"alert_start_timestamp","description":"alert_start_timestamp","type":"string"},"alert_title":{"title":"Title","description":"alert_title","type":"string"},"alert_uid":{"title":"alert_uid","description":"alert_uid","type":"string"},"observables":{"title":"observables","description":"observables","type":"array","items":{"type":"object","properties":{"observable_enrichments":{"title":"observable_enrichments","description":"observable_enrichments","type":"array","items":{"type":"object","properties":{"enrichment_context":{"title":"enrichment_context","description":"enrichment_context","type":"string"},"enrichment_permalink":{"title":"enrichment_permalink","description":"enrichment_permalink","type":"string"},"enrichment_provider":{"title":"enrichment_provider","description":"The enrichment data provider name.","type":"string"},"enrichment_raw_data":{"title":"enrichment_raw-data","description":"enrichment_raw-data","type":"string"},"enrichment_timestamp":{"title":"enrichment_timestamp","description":"Datetime the enrichment was retrieved","type":"string"},"enrichment_type":{"title":"enrichment_type","description":"The enrichment type. For example: location","type":"string"},"enrichment_verdict":{"title":"enrichment_verdict","description":"The reputation verdict","type":"string"}},"required":["enrichment_type"]}},"observable_metadata":{"title":"observable_metadata","description":"Observable Metadata","type":"object"},"observable_primary_context":{"title":"observable_primary_context","description":"observable_primary_context","type":"string"},"observable_primary_permalink":{"title":"observable_primary_permalink","description":"observable_primary_permalink","type":"string"},"observable_primary_provider":{"title":"observable_primary_provider","description":"observable_primary_provider","type":"string"},"observable_primary_timestamp":{"title":"observable_primary_timestamp","description":"observable_primary_timestamp","type":"string"},"observable_primary_verdict":{"title":"observable_primary_verdict","description":"observable_primary_verdict","type":"string"},"observable_type":{"title":"observable_type","description":"observable_type","type":"string"},"observable_value":{"title":"observable_value","description":"observable_value","type":"string"}},"required":["observable_type","observable_value"]}},"raw_alert":{"title":"raw_alert","description":"raw_alert","type":"object"}}}}},"meta":{},"name":"component_aS9A5tmGDMK9dzNgm_playbook","namespace":"$default","pool":"","publish":{"alert":{"$:ref":"$inputs.alert"}},"schema":"playbook/2","timeout":0.0,"title":"component_aS9A5tmGDMK9dzNgm_playbook","triggers":{},"uuid":"00000000-0000-0000-0000-000000000000"}}